keywordsai/__init__.py
keywordsai/constants/__init__.py
keywordsai/constants/dataset_constants.py
keywordsai/constants/evaluator_constants.py
keywordsai/constants/experiment_constants.py
keywordsai/constants/log_constants.py
keywordsai/constants/prompt_constants.py
keywordsai/datasets/__init__.py
keywordsai/datasets/api.py
keywordsai/evaluators/__init__.py
keywordsai/evaluators/api.py
keywordsai/experiments/__init__.py
keywordsai/experiments/api.py
keywordsai/logs/__init__.py
keywordsai/logs/api.py
keywordsai/prompts/README.md
keywordsai/prompts/__init__.py
keywordsai/prompts/api.py
keywordsai/types/__init__.py
keywordsai/types/dataset_types.py
keywordsai/types/evaluator_types.py
keywordsai/types/experiment_types.py
keywordsai/types/generic_types.py
keywordsai/types/log_types.py
keywordsai/types/prompt_types.py
keywordsai/users/__init__.py
keywordsai/utils/__init__.py
keywordsai/utils/base.py
keywordsai/utils/client.py
keywordsai/utils/mixins.py
keywordsai-1.0.4.dist-info/METADATA
keywordsai-1.0.4.dist-info/WHEEL
keywordsai-1.0.4.dist-info/RECORD
