Metadata-Version: 2.1
Name: keywordsai
Version: 1.0.4
Summary: A package that helps interacting with Keywords AI monitoring, evaluation & user analytics APIs
License: Apache 2.0
Author: Raymond Huang
Author-email: raymond@keywordsai.co
Requires-Python: >3.9,<4.0
Classifier: License :: Other/Proprietary License
Classifier: Programming Language :: Python :: 3
Classifier: Programming Language :: Python :: 3.10
Classifier: Programming Language :: Python :: 3.11
Classifier: Programming Language :: Python :: 3.12
Requires-Dist: httpx (>=0.28.1,<0.29.0)
Requires-Dist: keywordsai-sdk (>=0.4.83,<0.5.0)
